nmap3/__init__.py
nmap3/exceptions.py
nmap3/nmap3.py
nmap3/nmapparser.py
nmap3/utils.py
python3_nmap-1.5.4.dist-info/LICENSE
python3_nmap-1.5.4.dist-info/METADATA
python3_nmap-1.5.4.dist-info/WHEEL
python3_nmap-1.5.4.dist-info/top_level.txt
python3_nmap-1.5.4.dist-info/RECORD
