Metadata-Version: 2.1
Name: python3-nmap
Version: 1.5.4
Summary: Python3-nmap converts Nmap commands into python3 methods making it very easy to use nmap in any of your python pentesting projects
Home-page: https://github.com/wangoloj/python3-nmap
Author: nmmapper
Author-email: info@nmmapper.com
License: UNKNOWN
Project-URL: Documentation, https://nmap.readthedocs.io/en/latest/
Project-URL: How it is used, https://www.nmmapper.com/sys/networkmapper/nmap/online-port-scanning/
Project-URL: Homepage, https://www.nmmapper.com/
Project-URL: Source, https://github.com/wangoloj/python3-nmap
Project-URL: Subdomain finder, https://www.nmmapper.com/sys/tools/subdomainfinder/
Project-URL: theHarvester online, https://www.nmmapper.com/sys/theharvester/email-harvester-tool/online/
Project-URL: Crosselling, https://www.byogyo.com/
Platform: UNKNOWN
Classifier: Programming Language :: Python :: 3
Classifier: License :: OSI Approved :: MIT License
Classifier: Operating System :: OS Independent
Requires-Python: >=3.6
Requires-Dist: simplejson
